htagweb/__init__.py
htagweb/crypto.py
htagweb/fifo.py
htagweb/fqn.py
htagweb/hrclient.py
htagweb/hrprocess.py
htagweb/manage.py
htagweb/runners.py
htagweb/serverredys.py
htagweb/session.py
htagweb-0.60.3.dist-info/METADATA
htagweb-0.60.3.dist-info/WHEEL
htagweb-0.60.3.dist-info/licenses/LICENSE
htagweb-0.60.3.dist-info/RECORD
