Metadata-Version: 2.4
Name: htagweb
Version: 0.60.3
Summary: It's a robust webserver (http/ws) for hosting htag apps on the web (a process by user)
Project-URL: Homepage, https://github.com/manatlan/htagweb
Project-URL: Repository, https://github.com/manatlan/htagweb
Project-URL: Documentation, https://github.com/manatlan/htagweb
Author-email: manatlan <manatlan@gmail.com>
License: MIT
License-File: LICENSE
Keywords: htag,webserver
Classifier: License :: OSI Approved :: Apache Software License
Classifier: Operating System :: OS Independent
Classifier: Topic :: Software Development :: Build Tools
Classifier: Topic :: Software Development :: Libraries :: Python Modules
Requires-Python: >=3.8
Requires-Dist: htag>=0.51
Requires-Dist: pycryptodomex>=3.19.0
Requires-Dist: shared-memory-dict>=0.7.2
Requires-Dist: starlette>=0.40.0
Requires-Dist: uvicorn[standard]==0.30.0
